{
  "municipality": "SAN LUIS DE LA PAZ",
  "municipalityCode": "033",
  "state": "GUANAJUATO",
  "stateCode": "11",
  "tables": [
    {
      "tableIndex": 0,
      "data": [
        [
          "Ciclo escolar:\n                            \n\t2024-2025\n\t2023-2024\n\t2022-2023\n\t2021-2022\n\t2020-2021\n\t2019-2020\n\t2018-2019\n\t2017-2018\n\t2016-2017\n\n\n                            \n\n                        \n                    \n                    \n                        \n                            Modalidad:\n                            \n\tSelecciona\n\tEscolarizada\n\tNo Escolarizada\n\tAmbas modalidades\n\n\n                        \n                    \n                    \n                        \n                            Tipo educativo:\n                            \n\tTodos\n\n\n                        \n                    \n                    \n                        \n                            Nivel educativo:\n                            \n\tTodos\n\n\n                        \n                    \n                    \n                        \n                            Servicio educativo:\n                            \n\tTodos"
        ],
        [
          "Sostenimiento (Control administrativo):\n                            \n\tTodos\n\tPúblico\n\tPrivado\n\n\n                        \n                    \n                    \n                        \n                            Subcontrol administrativo:                            \n                            \n\tTodos\n\n\n                            \n                        \n                    \n                    \n                        \n                            Entidad federativa:\n                            \n\tTodas\n\tAGUASCALIENTES\n\tBAJA CALIFORNIA\n\tBAJA CALIFORNIA SUR\n\tCAMPECHE\n\tCOAHUILA DE ZARAGOZA\n\tCOLIMA\n\tCHIAPAS\n\tCHIHUAHUA\n\tCIUDAD DE MÉXICO\n\tDURANGO\n\tGUANAJUATO\n\tGUERRERO\n\tHIDALGO\n\tJALISCO\n\tMÉXICO\n\tMICHOACÁN DE OCAMPO\n\tMORELOS\n\tNAYARIT\n\tNUEVO LEÓN\n\tOAXACA\n\tPUEBLA\n\tQUERÉTARO\n\tQUINTANA ROO\n\tSAN LUIS POTOSÍ\n\tSINALOA\n\tSONORA\n\tTABASCO\n\tTAMAULIPAS\n\tTLAXCALA\n\tVERACRUZ DE IGNACIO DE LA LLAVE\n\tYUCATÁN\n\tZACATECAS\n\n\n                        \n                    \n                    \n                        \n                            Municipio:\n                            \n\tTodos\n\tABASOLO\n\tACÁMBARO\n\tAPASEO EL ALTO\n\tAPASEO EL GRANDE\n\tATARJEA\n\tCELAYA\n\tCOMONFORT\n\tCORONEO\n\tCORTAZAR\n\tCUERÁMARO\n\tDOCTOR MORA\n\tDOLORES HIDALGO CUNA DE LA INDEPENDENCIA NACIONAL\n\tGUANAJUATO\n\tHUANÍMARO\n\tIRAPUATO\n\tJARAL DEL PROGRESO\n\tJERÉCUARO\n\tLEÓN\n\tMANUEL DOBLADO\n\tMOROLEÓN\n\tOCAMPO\n\tPÉNJAMO\n\tPUEBLO NUEVO\n\tPURÍSIMA DEL RINCÓN\n\tROMITA\n\tSALAMANCA\n\tSALVATIERRA\n\tSAN DIEGO DE LA UNIÓN\n\tSAN FELIPE\n\tSAN FRANCISCO DEL RINCÓN\n\tSAN JOSÉ ITURBIDE\n\tSAN LUIS DE LA PAZ\n\tSAN MIGUEL DE ALLENDE\n\tSANTA CATARINA\n\tSANTA CRUZ DE JUVENTINO ROSAS\n\tSANTIAGO MARAVATÍO\n\tSILAO DE LA VICTORIA\n\tTARANDACUAO\n\tTARIMORO\n\tTIERRA BLANCA\n\tURIANGATO\n\tVALLE DE SANTIAGO\n\tVICTORIA\n\tVILLAGRÁN\n\tXICHÚ\n\tYURIRIA"
        ]
      ]
    },
    {
      "tableIndex": 1,
      "data": [
        [
          "TIPO EDUCATIVO: TODOS;     CONTROL: TODOS;     ENTIDAD: GUANAJUATO;    MUNICIPIO: SAN LUIS DE LA PAZ\n\t\n\t\n\t\tLocalidad\n\t\tEscuelas\n\t\tAlumnos\n\t\tAlumnos Mujeres\n\t\tAlumnos Hombres\n\t\tDocentes¹\n\t\n\t\n\t\tBERLÍN\n\t\t1\n\t\t114\n\t\t67\n\t\t47\n\t\t6\n\t\n\t\n\t\tBUENAVISTA (EL CUERNITO)\n\t\t2\n\t\t135\n\t\t63\n\t\t72\n\t\t9\n\t\n\t\n\t\tCERRO BLANCO\n\t\t2\n\t\t5\n\t\t1\n\t\t4\n\t\t2\n\t\n\t\n\t\tCOLONIA BENITO JUÁREZ\n\t\t1\n\t\t51\n\t\t20\n\t\t31\n\t\t3\n\t\n\t\n\t\tCOVADONGA\n\t\t2\n\t\t131\n\t\t48\n\t\t83\n\t\t7\n\t\n\t\n\t\tDERRAMADERO SEGUNDO (INFIERNILLO)\n\t\t4\n\t\t316\n\t\t154\n\t\t162\n\t\t15\n\t\n\t\n\t\tDOLORES SAN JUAN\n\t\t2\n\t\t100\n\t\t51\n\t\t49\n\t\t5\n\t\n\t\n\t\tEJIDO SANTA ANA Y LOBOS (FRACCIÓN DE LOURDES)\n\t\t5\n\t\t853\n\t\t443\n\t\t410\n\t\t30\n\t\n\t\n\t\tEL BOLUDO\n\t\t1\n\t\t11\n\t\t4\n\t\t7\n\t\t1\n\t\n\t\n\t\tEL BOZO\n\t\t2\n\t\t24\n\t\t10\n\t\t14\n\t\t2\n\t\n\t\n\t\tEL CHARCO\n\t\t2\n\t\t173\n\t\t93\n\t\t80\n\t\t8\n\t\n\t\n\t\tEL CHUPADERO\n\t\t4\n\t\t112\n\t\t59\n\t\t53\n\t\t9\n\t\n\t\n\t\tEL MEZOTE (ENTRONQUE DE CHARCAS)\n\t\t1\n\t\t10\n\t\t4\n\t\t6\n\t\t1\n\t\n\t\n\t\tEL PAREDÓN\n\t\t1\n\t\t10\n\t\t8\n\t\t2\n\t\t1\n\t\n\t\n\t\tEL PRINGÓN\n\t\t2\n\t\t109\n\t\t51\n\t\t58\n\t\t5\n\t\n\t\n\t\tEL REALITO (MINERAL EL REALITO)\n\t\t2\n\t\t14\n\t\t4\n\t\t10\n\t\t2\n\t\n\t\n\t\tEL REFUGIO (RANCHITO EL REFUGIO)\n\t\t2\n\t\t38\n\t\t22\n\t\t16\n\t\t2\n\t\n\t\n\t\tEL SAUZ TRES\n\t\t2\n\t\t179\n\t\t92\n\t\t87\n\t\t8\n\t\n\t\n\t\tEL TOREADOR DE ABAJO\n\t\t2\n\t\t227\n\t\t120\n\t\t107\n\t\t8\n\t\n\t\n\t\tEL VARAL (LA MERCED)\n\t\t4\n\t\t344\n\t\t173\n\t\t171\n\t\t13\n\t\n\t\n\t\tESPINAS BLANCAS\n\t\t2\n\t\t64\n\t\t37\n\t\t27\n\t\t3\n\t\n\t\n\t\tEX-HACIENDA DE ORTEGA (EJIDO ORTEGA)\n\t\t4\n\t\t210\n\t\t86\n\t\t124\n\t\t12\n\t\n\t\n\t\tEX-HACIENDA DE SANTA ANA (SANTA ANA Y LOBOS)\n\t\t1\n\t\t218\n\t\t94\n\t\t124\n\t\t8\n\t\n\t\n\t\tFRACCIONAMIENTO RESIDENCIAL VILLAS DE LA GLORIA\n\t\t1\n\t\t50\n\t\t23\n\t\t27\n\t\t12\n\t\n\t\n\t\tGARIBALDI (EL CERRITO)\n\t\t2\n\t\t28\n\t\t13\n\t\t15\n\t\t2\n\t\n\t\n\t\tJOFRE (SAN JOSÉ DE JOFRE)\n\t\t1\n\t\t8\n\t\t0\n\t\t8\n\t\t1\n\t\n\t\n\t\tLA ANGELINA (LOS LIEBRILLOS)\n\t\t2\n\t\t50\n\t\t28\n\t\t22\n\t\t3\n\t\n\t\n\t\tLA CANTERA\n\t\t2\n\t\t92\n\t\t44\n\t\t48\n\t\t5\n\t\n\t\n\t\tLA CAÑADA DEL PUEBLITO\n\t\t1\n\t\t8\n\t\t4\n\t\t4\n\t\t1\n\t\n\t\n\t\tLA CIÉNEGA\n\t\t3\n\t\t417\n\t\t212\n\t\t205\n\t\t19\n\t\n\t\n\t\tLA CIENEGUILLA DEL REFUGIO\n\t\t2\n\t\t55\n\t\t22\n\t\t33\n\t\t4\n\t\n\t\n\t\tLA CONCEPCIÓN (LA CONCHA)\n\t\t1\n\t\t8\n\t\t5\n\t\t3\n\t\t1\n\t\n\t\n\t\tLA CRUZ\n\t\t1\n\t\t18\n\t\t8\n\t\t10\n\t\t2\n\t\n\t\n\t\tLA CRUZ DE GUERRERO\n\t\t4\n\t\t194\n\t\t99\n\t\t95\n\t\t10\n\t\n\t\n\t\tLA ESCOBILLA\n\t\t2\n\t\t42\n\t\t21\n\t\t21\n\t\t3\n\t\n\t\n\t\tLA ESCONDIDA\n\t\t1\n\t\t6\n\t\t4\n\t\t2\n\t\t1\n\t\n\t\n\t\tLA ESCONDIDITA\n\t\t3\n\t\t157\n\t\t75\n\t\t82\n\t\t10\n\t\n\t\n\t\tLA ESQUINA (LA ESQUINA DE LA PURÍSIMA)\n\t\t4\n\t\t221\n\t\t125\n\t\t96\n\t\t10\n\t\n\t\n\t\tLA HUERTA\n\t\t4\n\t\t1,991\n\t\t1,101\n\t\t890\n\t\t154\n\t\n\t\n\t\tLA JARRILLA\n\t\t2\n\t\t39\n\t\t27\n\t\t12\n\t\t2\n\t\n\t\n\t\tLA LAGUNA SECA\n\t\t2\n\t\t165\n\t\t79\n\t\t86\n\t\t8\n\t\n\t\n\t\tLA LEONA\n\t\t2\n\t\t62\n\t\t36\n\t\t26\n\t\t3\n\t\n\t\n\t\tLA LUZ\n\t\t2\n\t\t32\n\t\t16\n\t\t16\n\t\t2\n\t\n\t\n\t\tLA LUZ DE LA ESQUINA\n\t\t4\n\t\t408\n\t\t199\n\t\t209\n\t\t17\n\t\n\t\n\t\tLA MESA DE JESÚS\n\t\t4\n\t\t95\n\t\t48\n\t\t47\n\t\t8\n\t\n\t\n\t\tLA ONZA\n\t\t2\n\t\t14\n\t\t9\n\t\t5\n\t\t2\n\t\n\t\n\t\tLA PEÑITA\n\t\t1\n\t\t49\n\t\t23\n\t\t26\n\t\t3\n\t\n\t\n\t\tLA PROVIDENCIA (LA PROVIDENCIA DEL SALITRE)\n\t\t2\n\t\t52\n\t\t30\n\t\t22\n\t\t4\n\t\n\t\n\t\tLA QUINTA DOS\n\t\t2\n\t\t33\n\t\t17\n\t\t16\n\t\t2\n\t\n\t\n\t\tLA SEMITA\n\t\t4\n\t\t112\n\t\t54\n\t\t58\n\t\t8\n\t\n\t\n\t\tLA SOLEDAD\n\t\t3\n\t\t206\n\t\t107\n\t\t99\n\t\t11\n\t\n\t\n\t\tLA SOLEDAD DEL MONTE\n\t\t3\n\t\t97\n\t\t43\n\t\t54\n\t\t6\n\t\n\t\n\t\tLA TINAJA\n\t\t2\n\t\t88\n\t\t41\n\t\t47\n\t\t4\n\t\n\t\n\t\tLA VACIADA\n\t\t2\n\t\t31\n\t\t16\n\t\t15\n\t\t2\n\t\n\t\n\t\tLABOR DE GAMBOA\n\t\t2\n\t\t66\n\t\t37\n\t\t29\n\t\t3\n\t\n\t\n\t\tLAS NEGRITAS\n\t\t2\n\t\t44\n\t\t22\n\t\t22\n\t\t2\n\t\n\t\n\t\tLAS PALOMAS\n\t\t1\n\t\t6\n\t\t3\n\t\t3\n\t\t1\n\t\n\t\n\t\tLOS ÁNGELES\n\t\t4\n\t\t371\n\t\t208\n\t\t163\n\t\t15\n\t\n\t\n\t\tLOS DOLORES (LAS QUINCE LETRAS)\n\t\t6\n\t\t1,149\n\t\t583\n\t\t566\n\t\t38\n\t\n\t\n\t\tLOS PLÁTANOS\n\t\t2\n\t\t41\n\t\t22\n\t\t19\n\t\t3\n\t\n\t\n\t\tLOS REMEDIOS\n\t\t2\n\t\t52\n\t\t25\n\t\t27\n\t\t3\n\t\n\t\n\t\tLOURDES (ESTACIÓN DE LOURDES)\n\t\t4\n\t\t500\n\t\t255\n\t\t245\n\t\t20\n\t\n\t\n\t\tMAGUEY BLANCO\n\t\t2\n\t\t175\n\t\t89\n\t\t86\n\t\t7\n\t\n\t\n\t\tMANZANARES\n\t\t2\n\t\t57\n\t\t26\n\t\t31\n\t\t3\n\t\n\t\n\t\tMARAVILLAL\n\t\t2\n\t\t257\n\t\t129\n\t\t128\n\t\t9\n\t\n\t\n\t\tMATANCILLAS (PUERTO DE MATANCILLAS)\n\t\t2\n\t\t59\n\t\t31\n\t\t28\n\t\t4\n\t\n\t\n\t\tMESA DE ESCALANTE\n\t\t2\n\t\t26\n\t\t13\n\t\t13\n\t\t2\n\t\n\t\n\t\tMESA DE LA ESTACADA\n\t\t2\n\t\t16\n\t\t6\n\t\t10\n\t\t2\n\t\n\t\n\t\tMESA DE PALOTES (MESA DEL CARMEN)\n\t\t2\n\t\t36\n\t\t23\n\t\t13\n\t\t2\n\t\n\t\n\t\tMISIÓN DE CHICHIMECAS\n\t\t9\n\t\t2,271\n\t\t1,193\n\t\t1,078\n\t\t88\n\t\n\t\n\t\tNORITA DEL REFUGIO\n\t\t3\n\t\t129\n\t\t59\n\t\t70\n\t\t7\n\t\n\t\n\t\tNUEVO PASO DE VAQUEROS\n\t\t2\n\t\t61\n\t\t24\n\t\t37\n\t\t4\n\t\n\t\n\t\tPALMARITO\n\t\t2\n\t\t33\n\t\t12\n\t\t21\n\t\t2\n\t\n\t\n\t\tPALMILLAS\n\t\t1\n\t\t6\n\t\t0\n\t\t6\n\t\t1\n\t\n\t\n\t\tPALOS ALTOS\n\t\t2\n\t\t174\n\t\t94\n\t\t80\n\t\t8\n\t\n\t\n\t\tPAREDES\n\t\t2\n\t\t96\n\t\t43\n\t\t53\n\t\t5\n\t\n\t\n\t\tPASO COLORADO\n\t\t2\n\t\t50\n\t\t24\n\t\t26\n\t\t2\n\t\n\t\n\t\tPIEDRAS DE LUMBRE\n\t\t2\n\t\t90\n\t\t35\n\t\t55\n\t\t5\n\t\n\t\n\t\tPOZO BLANCO\n\t\t3\n\t\t177\n\t\t96\n\t\t81\n\t\t8\n\t\n\t\n\t\tPOZO BLANCO (ESTACIÓN POZO BLANCO)\n\t\t3\n\t\t185\n\t\t99\n\t\t86\n\t\t9\n\t\n\t\n\t\tPOZO HONDO (EX-HACIENDA DE POZO HONDO)\n\t\t3\n\t\t232\n\t\t124\n\t\t108\n\t\t11\n\t\n\t\n\t\tPROVIDENCIA DE LOS MOLINA\n\t\t4\n\t\t181\n\t\t97\n\t\t84\n\t\t10\n\t\n\t\n\t\tPUERTO BLANCO DOS\n\t\t3\n\t\t352\n\t\t192\n\t\t160\n\t\t13\n\t\n\t\n\t\tPUERTO DEL GATO\n\t\t2\n\t\t33\n\t\t16\n\t\t17\n\t\t2\n\t\n\t\n\t\tPUERTO DEL VARAL\n\t\t2\n\t\t8\n\t\t1\n\t\t7\n\t\t2\n\t\n\t\n\t\tPURÍSIMA DE CERRO GRANDE\n\t\t2\n\t\t70\n\t\t36\n\t\t34\n\t\t4\n\t\n\t\n\t\tRANCHO DE GUADALUPE (CIUDAD DE LOS NIÑOS)\n\t\t2\n\t\t29\n\t\t17\n\t\t12\n\t\t2\n\t\n\t\n\t\tRANCHO NUEVO\n\t\t2\n\t\t60\n\t\t26\n\t\t34\n\t\t3\n\t\n\t\n\t\tRANCHO NUEVO DE LAS TROJES\n\t\t2\n\t\t14\n\t\t7\n\t\t7\n\t\t2\n\t\n\t\n\t\tSAN AGUSTÍN\n\t\t2\n\t\t93\n\t\t44\n\t\t49\n\t\t5\n\t\n\t\n\t\tSAN AGUSTÍN SEGUNDO\n\t\t1\n\t\t10\n\t\t7\n\t\t3\n\t\t1\n\t\n\t\n\t\tSAN ANTÓN DE LOS MARTÍNEZ\n\t\t2\n\t\t24\n\t\t10\n\t\t14\n\t\t2\n\t\n\t\n\t\tSAN ANTONIO DE LAS VIEJAS\n\t\t2\n\t\t23\n\t\t12\n\t\t11\n\t\t2\n\t\n\t\n\t\tSAN ANTONIO DE PADUA\n\t\t1\n\t\t12\n\t\t7\n\t\t5\n\t\t1\n\t\n\t\n\t\tSAN ANTONIO PRIMERO\n\t\t2\n\t\t177\n\t\t86\n\t\t91\n\t\t8\n\t\n\t\n\t\tSAN CAYETANO\n\t\t2\n\t\t163\n\t\t89\n\t\t74\n\t\t6\n\t\n\t\n\t\tSAN ERNESTO\n\t\t2\n\t\t146\n\t\t67\n\t\t79\n\t\t8\n\t\n\t\n\t\tSAN FRANCISCO UNO\n\t\t2\n\t\t22\n\t\t7\n\t\t15\n\t\t2\n\t\n\t\n\t\tSAN IGNACIO\n\t\t1\n\t\t47\n\t\t28\n\t\t19\n\t\t2\n\t\n\t\n\t\tSAN ISIDRO\n\t\t4\n\t\t436\n\t\t222\n\t\t214\n\t\t17\n\t\n\t\n\t\tSAN JOSÉ DE VISTA HERMOSA\n\t\t2\n\t\t36\n\t\t17\n\t\t19\n\t\t2\n\t\n\t\n\t\tSAN JOSÉ DEL CARMEN (EL CASCARERO)\n\t\t2\n\t\t122\n\t\t59\n\t\t63\n\t\t6\n\t\n\t\n\t\tSAN JUAN DE LA CRUZ\n\t\t2\n\t\t49\n\t\t25\n\t\t24\n\t\t3\n\t\n\t\n\t\tSAN JUAN DE LOS RANGELES\n\t\t2\n\t\t41\n\t\t18\n\t\t23\n\t\t2\n\t\n\t\n\t\tSAN JUAN PRIMERO\n\t\t2\n\t\t127\n\t\t61\n\t\t66\n\t\t6\n\t\n\t\n\t\tSAN JUAN SEGUNDO\n\t\t2\n\t\t28\n\t\t15\n\t\t13\n\t\t2\n\t\n\t\n\t\tSAN LUIS DE LA PAZ\n\t\t76\n\t\t16,585\n\t\t8,612\n\t\t7,973\n\t\t917\n\t\n\t\n\t\tSAN MARTÍN\n\t\t2\n\t\t80\n\t\t39\n\t\t41\n\t\t5\n\t\n\t\n\t\tSAN NICOLÁS DEL CARMEN\n\t\t6\n\t\t946\n\t\t455\n\t\t491\n\t\t45\n\t\n\t\n\t\tSAN PEDRO\n\t\t2\n\t\t40\n\t\t20\n\t\t20\n\t\t3\n\t\n\t\n\t\tSAN PEDRO DE LA CRUZ\n\t\t2\n\t\t118\n\t\t58\n\t\t60\n\t\t6\n\t\n\t\n\t\tSAN PEDRO DE LOS POZOS (MINERAL DE POZOS)\n\t\t6\n\t\t882\n\t\t411\n\t\t471\n\t\t51\n\t\n\t\n\t\tSAN PEDRO DEL DERRAMADERO (LOS PIRULES)\n\t\t1\n\t\t16\n\t\t11\n\t\t5\n\t\t1\n\t\n\t\n\t\tSAN RAFAEL\n\t\t1\n\t\t68\n\t\t38\n\t\t30\n\t\t3\n\t\n\t\n\t\tSAN RAFAEL DE FÁTIMA\n\t\t2\n\t\t48\n\t\t23\n\t\t25\n\t\t3\n\t\n\t\n\t\tSAN RAFAEL DE LA CURVA\n\t\t1\n\t\t27\n\t\t12\n\t\t15\n\t\t1\n\t\n\t\n\t\tSANTA MARÍA DE GUADALUPE\n\t\t1\n\t\t11\n\t\t5\n\t\t6\n\t\t1\n\t\n\t\n\t\tSANTA ROSA DE OCHOA\n\t\t1\n\t\t58\n\t\t33\n\t\t25\n\t\t3\n\t\n\t\n\t\tSANTA TERESITA\n\t\t2\n\t\t50\n\t\t25\n\t\t25\n\t\t3\n\t\n\t\n\t\tSANTIAGUILLO\n\t\t1\n\t\t5\n\t\t1\n\t\t4\n\t\t1\n\t\n\t\n\t\tTERREROS DE LA CONCEPCIÓN\n\t\t3\n\t\t67\n\t\t26\n\t\t41\n\t\t5\n\t\n\t\n\t\tTOREADOR DE ARRIBA\n\t\t1\n\t\t13\n\t\t7\n\t\t6\n\t\t1\n\t\n\t\n\t\tTOREADOR DE EN MEDIO\n\t\t3\n\t\t337\n\t\t151\n\t\t186\n\t\t14\n\t\n\t\n\t\tVALLE DE GUADALUPE\n\t\t1\n\t\t87\n\t\t40\n\t\t47\n\t\t4\n\t\n\t\n\t\tVERGEL DE GUADALUPE\n\t\t3\n\t\t174\n\t\t89\n\t\t85\n\t\t8\n\t\n\t\n\t\tVISTA HERMOSA\n\t\t3\n\t\t114\n\t\t69\n\t\t45\n\t\t8\n\t\n\t\n\t\tXOCONOXTLE\n\t\t1\n\t\t16\n\t\t9\n\t\t7\n\t\t1\n\t\n\t\n\t\tZAMARRIPA (SAN JOSÉ DE ZAMARRIPA)\n\t\t2\n\t\t39\n\t\t18\n\t\t21\n\t\t2\n\t\n\t\n\t\tTOTAL\n\t\t366\n\t\t36,719\n\t\t18,826\n\t\t17,893\n\t\t1,943\n\t\n\t\n\t\t¹   Conjunto de individuos adscritos a un centro de trabajo, de acuerdo a la función que realizan en el mismo. A cada uno se le considera tantas veces como en centros de trabajo esté adscrito.\n\t\n\t\n\t\t  Fuente: Sistema de Estadísticas Continuas de Educación del Formato 911, DGPPyEE, SEP.",
          "TIPO EDUCATIVO: TODOS;     CONTROL: TODOS;     ENTIDAD: GUANAJUATO;    MUNICIPIO: SAN LUIS DE LA PAZ",
          "Localidad",
          "Escuelas",
          "Alumnos",
          "Alumnos Mujeres",
          "Alumnos Hombres",
          "Docentes¹",
          "BERLÍN",
          "1",
          "114",
          "67",
          "47",
          "6",
          "BUENAVISTA (EL CUERNITO)",
          "2",
          "135",
          "63",
          "72",
          "9",
          "CERRO BLANCO",
          "2",
          "5",
          "1",
          "4",
          "2",
          "COLONIA BENITO JUÁREZ",
          "1",
          "51",
          "20",
          "31",
          "3",
          "COVADONGA",
          "2",
          "131",
          "48",
          "83",
          "7",
          "DERRAMADERO SEGUNDO (INFIERNILLO)",
          "4",
          "316",
          "154",
          "162",
          "15",
          "DOLORES SAN JUAN",
          "2",
          "100",
          "51",
          "49",
          "5",
          "EJIDO SANTA ANA Y LOBOS (FRACCIÓN DE LOURDES)",
          "5",
          "853",
          "443",
          "410",
          "30",
          "EL BOLUDO",
          "1",
          "11",
          "4",
          "7",
          "1",
          "EL BOZO",
          "2",
          "24",
          "10",
          "14",
          "2",
          "EL CHARCO",
          "2",
          "173",
          "93",
          "80",
          "8",
          "EL CHUPADERO",
          "4",
          "112",
          "59",
          "53",
          "9",
          "EL MEZOTE (ENTRONQUE DE CHARCAS)",
          "1",
          "10",
          "4",
          "6",
          "1",
          "EL PAREDÓN",
          "1",
          "10",
          "8",
          "2",
          "1",
          "EL PRINGÓN",
          "2",
          "109",
          "51",
          "58",
          "5",
          "EL REALITO (MINERAL EL REALITO)",
          "2",
          "14",
          "4",
          "10",
          "2",
          "EL REFUGIO (RANCHITO EL REFUGIO)",
          "2",
          "38",
          "22",
          "16",
          "2",
          "EL SAUZ TRES",
          "2",
          "179",
          "92",
          "87",
          "8",
          "EL TOREADOR DE ABAJO",
          "2",
          "227",
          "120",
          "107",
          "8",
          "EL VARAL (LA MERCED)",
          "4",
          "344",
          "173",
          "171",
          "13",
          "ESPINAS BLANCAS",
          "2",
          "64",
          "37",
          "27",
          "3",
          "EX-HACIENDA DE ORTEGA (EJIDO ORTEGA)",
          "4",
          "210",
          "86",
          "124",
          "12",
          "EX-HACIENDA DE SANTA ANA (SANTA ANA Y LOBOS)",
          "1",
          "218",
          "94",
          "124",
          "8",
          "FRACCIONAMIENTO RESIDENCIAL VILLAS DE LA GLORIA",
          "1",
          "50",
          "23",
          "27",
          "12",
          "GARIBALDI (EL CERRITO)",
          "2",
          "28",
          "13",
          "15",
          "2",
          "JOFRE (SAN JOSÉ DE JOFRE)",
          "1",
          "8",
          "0",
          "8",
          "1",
          "LA ANGELINA (LOS LIEBRILLOS)",
          "2",
          "50",
          "28",
          "22",
          "3",
          "LA CANTERA",
          "2",
          "92",
          "44",
          "48",
          "5",
          "LA CAÑADA DEL PUEBLITO",
          "1",
          "8",
          "4",
          "4",
          "1",
          "LA CIÉNEGA",
          "3",
          "417",
          "212",
          "205",
          "19",
          "LA CIENEGUILLA DEL REFUGIO",
          "2",
          "55",
          "22",
          "33",
          "4",
          "LA CONCEPCIÓN (LA CONCHA)",
          "1",
          "8",
          "5",
          "3",
          "1",
          "LA CRUZ",
          "1",
          "18",
          "8",
          "10",
          "2",
          "LA CRUZ DE GUERRERO",
          "4",
          "194",
          "99",
          "95",
          "10",
          "LA ESCOBILLA",
          "2",
          "42",
          "21",
          "21",
          "3",
          "LA ESCONDIDA",
          "1",
          "6",
          "4",
          "2",
          "1",
          "LA ESCONDIDITA",
          "3",
          "157",
          "75",
          "82",
          "10",
          "LA ESQUINA (LA ESQUINA DE LA PURÍSIMA)",
          "4",
          "221",
          "125",
          "96",
          "10",
          "LA HUERTA",
          "4",
          "1,991",
          "1,101",
          "890",
          "154",
          "LA JARRILLA",
          "2",
          "39",
          "27",
          "12",
          "2",
          "LA LAGUNA SECA",
          "2",
          "165",
          "79",
          "86",
          "8",
          "LA LEONA",
          "2",
          "62",
          "36",
          "26",
          "3",
          "LA LUZ",
          "2",
          "32",
          "16",
          "16",
          "2",
          "LA LUZ DE LA ESQUINA",
          "4",
          "408",
          "199",
          "209",
          "17",
          "LA MESA DE JESÚS",
          "4",
          "95",
          "48",
          "47",
          "8",
          "LA ONZA",
          "2",
          "14",
          "9",
          "5",
          "2",
          "LA PEÑITA",
          "1",
          "49",
          "23",
          "26",
          "3",
          "LA PROVIDENCIA (LA PROVIDENCIA DEL SALITRE)",
          "2",
          "52",
          "30",
          "22",
          "4",
          "LA QUINTA DOS",
          "2",
          "33",
          "17",
          "16",
          "2",
          "LA SEMITA",
          "4",
          "112",
          "54",
          "58",
          "8",
          "LA SOLEDAD",
          "3",
          "206",
          "107",
          "99",
          "11",
          "LA SOLEDAD DEL MONTE",
          "3",
          "97",
          "43",
          "54",
          "6",
          "LA TINAJA",
          "2",
          "88",
          "41",
          "47",
          "4",
          "LA VACIADA",
          "2",
          "31",
          "16",
          "15",
          "2",
          "LABOR DE GAMBOA",
          "2",
          "66",
          "37",
          "29",
          "3",
          "LAS NEGRITAS",
          "2",
          "44",
          "22",
          "22",
          "2",
          "LAS PALOMAS",
          "1",
          "6",
          "3",
          "3",
          "1",
          "LOS ÁNGELES",
          "4",
          "371",
          "208",
          "163",
          "15",
          "LOS DOLORES (LAS QUINCE LETRAS)",
          "6",
          "1,149",
          "583",
          "566",
          "38",
          "LOS PLÁTANOS",
          "2",
          "41",
          "22",
          "19",
          "3",
          "LOS REMEDIOS",
          "2",
          "52",
          "25",
          "27",
          "3",
          "LOURDES (ESTACIÓN DE LOURDES)",
          "4",
          "500",
          "255",
          "245",
          "20",
          "MAGUEY BLANCO",
          "2",
          "175",
          "89",
          "86",
          "7",
          "MANZANARES",
          "2",
          "57",
          "26",
          "31",
          "3",
          "MARAVILLAL",
          "2",
          "257",
          "129",
          "128",
          "9",
          "MATANCILLAS (PUERTO DE MATANCILLAS)",
          "2",
          "59",
          "31",
          "28",
          "4",
          "MESA DE ESCALANTE",
          "2",
          "26",
          "13",
          "13",
          "2",
          "MESA DE LA ESTACADA",
          "2",
          "16",
          "6",
          "10",
          "2",
          "MESA DE PALOTES (MESA DEL CARMEN)",
          "2",
          "36",
          "23",
          "13",
          "2",
          "MISIÓN DE CHICHIMECAS",
          "9",
          "2,271",
          "1,193",
          "1,078",
          "88",
          "NORITA DEL REFUGIO",
          "3",
          "129",
          "59",
          "70",
          "7",
          "NUEVO PASO DE VAQUEROS",
          "2",
          "61",
          "24",
          "37",
          "4",
          "PALMARITO",
          "2",
          "33",
          "12",
          "21",
          "2",
          "PALMILLAS",
          "1",
          "6",
          "0",
          "6",
          "1",
          "PALOS ALTOS",
          "2",
          "174",
          "94",
          "80",
          "8",
          "PAREDES",
          "2",
          "96",
          "43",
          "53",
          "5",
          "PASO COLORADO",
          "2",
          "50",
          "24",
          "26",
          "2",
          "PIEDRAS DE LUMBRE",
          "2",
          "90",
          "35",
          "55",
          "5",
          "POZO BLANCO",
          "3",
          "177",
          "96",
          "81",
          "8",
          "POZO BLANCO (ESTACIÓN POZO BLANCO)",
          "3",
          "185",
          "99",
          "86",
          "9",
          "POZO HONDO (EX-HACIENDA DE POZO HONDO)",
          "3",
          "232",
          "124",
          "108",
          "11",
          "PROVIDENCIA DE LOS MOLINA",
          "4",
          "181",
          "97",
          "84",
          "10",
          "PUERTO BLANCO DOS",
          "3",
          "352",
          "192",
          "160",
          "13",
          "PUERTO DEL GATO",
          "2",
          "33",
          "16",
          "17",
          "2",
          "PUERTO DEL VARAL",
          "2",
          "8",
          "1",
          "7",
          "2",
          "PURÍSIMA DE CERRO GRANDE",
          "2",
          "70",
          "36",
          "34",
          "4",
          "RANCHO DE GUADALUPE (CIUDAD DE LOS NIÑOS)",
          "2",
          "29",
          "17",
          "12",
          "2",
          "RANCHO NUEVO",
          "2",
          "60",
          "26",
          "34",
          "3",
          "RANCHO NUEVO DE LAS TROJES",
          "2",
          "14",
          "7",
          "7",
          "2",
          "SAN AGUSTÍN",
          "2",
          "93",
          "44",
          "49",
          "5",
          "SAN AGUSTÍN SEGUNDO",
          "1",
          "10",
          "7",
          "3",
          "1",
          "SAN ANTÓN DE LOS MARTÍNEZ",
          "2",
          "24",
          "10",
          "14",
          "2",
          "SAN ANTONIO DE LAS VIEJAS",
          "2",
          "23",
          "12",
          "11",
          "2",
          "SAN ANTONIO DE PADUA",
          "1",
          "12",
          "7",
          "5",
          "1",
          "SAN ANTONIO PRIMERO",
          "2",
          "177",
          "86",
          "91",
          "8",
          "SAN CAYETANO",
          "2",
          "163",
          "89",
          "74",
          "6",
          "SAN ERNESTO",
          "2",
          "146",
          "67",
          "79",
          "8",
          "SAN FRANCISCO UNO",
          "2",
          "22",
          "7",
          "15",
          "2",
          "SAN IGNACIO",
          "1",
          "47",
          "28",
          "19",
          "2",
          "SAN ISIDRO",
          "4",
          "436",
          "222",
          "214",
          "17",
          "SAN JOSÉ DE VISTA HERMOSA",
          "2",
          "36",
          "17",
          "19",
          "2",
          "SAN JOSÉ DEL CARMEN (EL CASCARERO)",
          "2",
          "122",
          "59",
          "63",
          "6",
          "SAN JUAN DE LA CRUZ",
          "2",
          "49",
          "25",
          "24",
          "3",
          "SAN JUAN DE LOS RANGELES",
          "2",
          "41",
          "18",
          "23",
          "2",
          "SAN JUAN PRIMERO",
          "2",
          "127",
          "61",
          "66",
          "6",
          "SAN JUAN SEGUNDO",
          "2",
          "28",
          "15",
          "13",
          "2",
          "SAN LUIS DE LA PAZ",
          "76",
          "16,585",
          "8,612",
          "7,973",
          "917",
          "SAN MARTÍN",
          "2",
          "80",
          "39",
          "41",
          "5",
          "SAN NICOLÁS DEL CARMEN",
          "6",
          "946",
          "455",
          "491",
          "45",
          "SAN PEDRO",
          "2",
          "40",
          "20",
          "20",
          "3",
          "SAN PEDRO DE LA CRUZ",
          "2",
          "118",
          "58",
          "60",
          "6",
          "SAN PEDRO DE LOS POZOS (MINERAL DE POZOS)",
          "6",
          "882",
          "411",
          "471",
          "51",
          "SAN PEDRO DEL DERRAMADERO (LOS PIRULES)",
          "1",
          "16",
          "11",
          "5",
          "1",
          "SAN RAFAEL",
          "1",
          "68",
          "38",
          "30",
          "3",
          "SAN RAFAEL DE FÁTIMA",
          "2",
          "48",
          "23",
          "25",
          "3",
          "SAN RAFAEL DE LA CURVA",
          "1",
          "27",
          "12",
          "15",
          "1",
          "SANTA MARÍA DE GUADALUPE",
          "1",
          "11",
          "5",
          "6",
          "1",
          "SANTA ROSA DE OCHOA",
          "1",
          "58",
          "33",
          "25",
          "3",
          "SANTA TERESITA",
          "2",
          "50",
          "25",
          "25",
          "3",
          "SANTIAGUILLO",
          "1",
          "5",
          "1",
          "4",
          "1",
          "TERREROS DE LA CONCEPCIÓN",
          "3",
          "67",
          "26",
          "41",
          "5",
          "TOREADOR DE ARRIBA",
          "1",
          "13",
          "7",
          "6",
          "1",
          "TOREADOR DE EN MEDIO",
          "3",
          "337",
          "151",
          "186",
          "14",
          "VALLE DE GUADALUPE",
          "1",
          "87",
          "40",
          "47",
          "4",
          "VERGEL DE GUADALUPE",
          "3",
          "174",
          "89",
          "85",
          "8",
          "VISTA HERMOSA",
          "3",
          "114",
          "69",
          "45",
          "8",
          "XOCONOXTLE",
          "1",
          "16",
          "9",
          "7",
          "1",
          "ZAMARRIPA (SAN JOSÉ DE ZAMARRIPA)",
          "2",
          "39",
          "18",
          "21",
          "2",
          "TOTAL",
          "366",
          "36,719",
          "18,826",
          "17,893",
          "1,943",
          "¹   Conjunto de individuos adscritos a un centro de trabajo, de acuerdo a la función que realizan en el mismo. A cada uno se le considera tantas veces como en centros de trabajo esté adscrito.",
          "Fuente: Sistema de Estadísticas Continuas de Educación del Formato 911, DGPPyEE, SEP."
        ],
        [
          "TIPO EDUCATIVO: TODOS;     CONTROL: TODOS;     ENTIDAD: GUANAJUATO;    MUNICIPIO: SAN LUIS DE LA PAZ"
        ],
        [
          "Localidad",
          "Escuelas",
          "Alumnos",
          "Alumnos Mujeres",
          "Alumnos Hombres",
          "Docentes¹"
        ],
        [
          "BERLÍN",
          "1",
          "114",
          "67",
          "47",
          "6"
        ],
        [
          "BUENAVISTA (EL CUERNITO)",
          "2",
          "135",
          "63",
          "72",
          "9"
        ],
        [
          "CERRO BLANCO",
          "2",
          "5",
          "1",
          "4",
          "2"
        ],
        [
          "COLONIA BENITO JUÁREZ",
          "1",
          "51",
          "20",
          "31",
          "3"
        ],
        [
          "COVADONGA",
          "2",
          "131",
          "48",
          "83",
          "7"
        ],
        [
          "DERRAMADERO SEGUNDO (INFIERNILLO)",
          "4",
          "316",
          "154",
          "162",
          "15"
        ],
        [
          "DOLORES SAN JUAN",
          "2",
          "100",
          "51",
          "49",
          "5"
        ],
        [
          "EJIDO SANTA ANA Y LOBOS (FRACCIÓN DE LOURDES)",
          "5",
          "853",
          "443",
          "410",
          "30"
        ],
        [
          "EL BOLUDO",
          "1",
          "11",
          "4",
          "7",
          "1"
        ],
        [
          "EL BOZO",
          "2",
          "24",
          "10",
          "14",
          "2"
        ],
        [
          "EL CHARCO",
          "2",
          "173",
          "93",
          "80",
          "8"
        ],
        [
          "EL CHUPADERO",
          "4",
          "112",
          "59",
          "53",
          "9"
        ],
        [
          "EL MEZOTE (ENTRONQUE DE CHARCAS)",
          "1",
          "10",
          "4",
          "6",
          "1"
        ],
        [
          "EL PAREDÓN",
          "1",
          "10",
          "8",
          "2",
          "1"
        ],
        [
          "EL PRINGÓN",
          "2",
          "109",
          "51",
          "58",
          "5"
        ],
        [
          "EL REALITO (MINERAL EL REALITO)",
          "2",
          "14",
          "4",
          "10",
          "2"
        ],
        [
          "EL REFUGIO (RANCHITO EL REFUGIO)",
          "2",
          "38",
          "22",
          "16",
          "2"
        ],
        [
          "EL SAUZ TRES",
          "2",
          "179",
          "92",
          "87",
          "8"
        ],
        [
          "EL TOREADOR DE ABAJO",
          "2",
          "227",
          "120",
          "107",
          "8"
        ],
        [
          "EL VARAL (LA MERCED)",
          "4",
          "344",
          "173",
          "171",
          "13"
        ],
        [
          "ESPINAS BLANCAS",
          "2",
          "64",
          "37",
          "27",
          "3"
        ],
        [
          "EX-HACIENDA DE ORTEGA (EJIDO ORTEGA)",
          "4",
          "210",
          "86",
          "124",
          "12"
        ],
        [
          "EX-HACIENDA DE SANTA ANA (SANTA ANA Y LOBOS)",
          "1",
          "218",
          "94",
          "124",
          "8"
        ],
        [
          "FRACCIONAMIENTO RESIDENCIAL VILLAS DE LA GLORIA",
          "1",
          "50",
          "23",
          "27",
          "12"
        ],
        [
          "GARIBALDI (EL CERRITO)",
          "2",
          "28",
          "13",
          "15",
          "2"
        ],
        [
          "JOFRE (SAN JOSÉ DE JOFRE)",
          "1",
          "8",
          "0",
          "8",
          "1"
        ],
        [
          "LA ANGELINA (LOS LIEBRILLOS)",
          "2",
          "50",
          "28",
          "22",
          "3"
        ],
        [
          "LA CANTERA",
          "2",
          "92",
          "44",
          "48",
          "5"
        ],
        [
          "LA CAÑADA DEL PUEBLITO",
          "1",
          "8",
          "4",
          "4",
          "1"
        ],
        [
          "LA CIÉNEGA",
          "3",
          "417",
          "212",
          "205",
          "19"
        ],
        [
          "LA CIENEGUILLA DEL REFUGIO",
          "2",
          "55",
          "22",
          "33",
          "4"
        ],
        [
          "LA CONCEPCIÓN (LA CONCHA)",
          "1",
          "8",
          "5",
          "3",
          "1"
        ],
        [
          "LA CRUZ",
          "1",
          "18",
          "8",
          "10",
          "2"
        ],
        [
          "LA CRUZ DE GUERRERO",
          "4",
          "194",
          "99",
          "95",
          "10"
        ],
        [
          "LA ESCOBILLA",
          "2",
          "42",
          "21",
          "21",
          "3"
        ],
        [
          "LA ESCONDIDA",
          "1",
          "6",
          "4",
          "2",
          "1"
        ],
        [
          "LA ESCONDIDITA",
          "3",
          "157",
          "75",
          "82",
          "10"
        ],
        [
          "LA ESQUINA (LA ESQUINA DE LA PURÍSIMA)",
          "4",
          "221",
          "125",
          "96",
          "10"
        ],
        [
          "LA HUERTA",
          "4",
          "1,991",
          "1,101",
          "890",
          "154"
        ],
        [
          "LA JARRILLA",
          "2",
          "39",
          "27",
          "12",
          "2"
        ],
        [
          "LA LAGUNA SECA",
          "2",
          "165",
          "79",
          "86",
          "8"
        ],
        [
          "LA LEONA",
          "2",
          "62",
          "36",
          "26",
          "3"
        ],
        [
          "LA LUZ",
          "2",
          "32",
          "16",
          "16",
          "2"
        ],
        [
          "LA LUZ DE LA ESQUINA",
          "4",
          "408",
          "199",
          "209",
          "17"
        ],
        [
          "LA MESA DE JESÚS",
          "4",
          "95",
          "48",
          "47",
          "8"
        ],
        [
          "LA ONZA",
          "2",
          "14",
          "9",
          "5",
          "2"
        ],
        [
          "LA PEÑITA",
          "1",
          "49",
          "23",
          "26",
          "3"
        ],
        [
          "LA PROVIDENCIA (LA PROVIDENCIA DEL SALITRE)",
          "2",
          "52",
          "30",
          "22",
          "4"
        ],
        [
          "LA QUINTA DOS",
          "2",
          "33",
          "17",
          "16",
          "2"
        ],
        [
          "LA SEMITA",
          "4",
          "112",
          "54",
          "58",
          "8"
        ],
        [
          "LA SOLEDAD",
          "3",
          "206",
          "107",
          "99",
          "11"
        ],
        [
          "LA SOLEDAD DEL MONTE",
          "3",
          "97",
          "43",
          "54",
          "6"
        ],
        [
          "LA TINAJA",
          "2",
          "88",
          "41",
          "47",
          "4"
        ],
        [
          "LA VACIADA",
          "2",
          "31",
          "16",
          "15",
          "2"
        ],
        [
          "LABOR DE GAMBOA",
          "2",
          "66",
          "37",
          "29",
          "3"
        ],
        [
          "LAS NEGRITAS",
          "2",
          "44",
          "22",
          "22",
          "2"
        ],
        [
          "LAS PALOMAS",
          "1",
          "6",
          "3",
          "3",
          "1"
        ],
        [
          "LOS ÁNGELES",
          "4",
          "371",
          "208",
          "163",
          "15"
        ],
        [
          "LOS DOLORES (LAS QUINCE LETRAS)",
          "6",
          "1,149",
          "583",
          "566",
          "38"
        ],
        [
          "LOS PLÁTANOS",
          "2",
          "41",
          "22",
          "19",
          "3"
        ],
        [
          "LOS REMEDIOS",
          "2",
          "52",
          "25",
          "27",
          "3"
        ],
        [
          "LOURDES (ESTACIÓN DE LOURDES)",
          "4",
          "500",
          "255",
          "245",
          "20"
        ],
        [
          "MAGUEY BLANCO",
          "2",
          "175",
          "89",
          "86",
          "7"
        ],
        [
          "MANZANARES",
          "2",
          "57",
          "26",
          "31",
          "3"
        ],
        [
          "MARAVILLAL",
          "2",
          "257",
          "129",
          "128",
          "9"
        ],
        [
          "MATANCILLAS (PUERTO DE MATANCILLAS)",
          "2",
          "59",
          "31",
          "28",
          "4"
        ],
        [
          "MESA DE ESCALANTE",
          "2",
          "26",
          "13",
          "13",
          "2"
        ],
        [
          "MESA DE LA ESTACADA",
          "2",
          "16",
          "6",
          "10",
          "2"
        ],
        [
          "MESA DE PALOTES (MESA DEL CARMEN)",
          "2",
          "36",
          "23",
          "13",
          "2"
        ],
        [
          "MISIÓN DE CHICHIMECAS",
          "9",
          "2,271",
          "1,193",
          "1,078",
          "88"
        ],
        [
          "NORITA DEL REFUGIO",
          "3",
          "129",
          "59",
          "70",
          "7"
        ],
        [
          "NUEVO PASO DE VAQUEROS",
          "2",
          "61",
          "24",
          "37",
          "4"
        ],
        [
          "PALMARITO",
          "2",
          "33",
          "12",
          "21",
          "2"
        ],
        [
          "PALMILLAS",
          "1",
          "6",
          "0",
          "6",
          "1"
        ],
        [
          "PALOS ALTOS",
          "2",
          "174",
          "94",
          "80",
          "8"
        ],
        [
          "PAREDES",
          "2",
          "96",
          "43",
          "53",
          "5"
        ],
        [
          "PASO COLORADO",
          "2",
          "50",
          "24",
          "26",
          "2"
        ],
        [
          "PIEDRAS DE LUMBRE",
          "2",
          "90",
          "35",
          "55",
          "5"
        ],
        [
          "POZO BLANCO",
          "3",
          "177",
          "96",
          "81",
          "8"
        ],
        [
          "POZO BLANCO (ESTACIÓN POZO BLANCO)",
          "3",
          "185",
          "99",
          "86",
          "9"
        ],
        [
          "POZO HONDO (EX-HACIENDA DE POZO HONDO)",
          "3",
          "232",
          "124",
          "108",
          "11"
        ],
        [
          "PROVIDENCIA DE LOS MOLINA",
          "4",
          "181",
          "97",
          "84",
          "10"
        ],
        [
          "PUERTO BLANCO DOS",
          "3",
          "352",
          "192",
          "160",
          "13"
        ],
        [
          "PUERTO DEL GATO",
          "2",
          "33",
          "16",
          "17",
          "2"
        ],
        [
          "PUERTO DEL VARAL",
          "2",
          "8",
          "1",
          "7",
          "2"
        ],
        [
          "PURÍSIMA DE CERRO GRANDE",
          "2",
          "70",
          "36",
          "34",
          "4"
        ],
        [
          "RANCHO DE GUADALUPE (CIUDAD DE LOS NIÑOS)",
          "2",
          "29",
          "17",
          "12",
          "2"
        ],
        [
          "RANCHO NUEVO",
          "2",
          "60",
          "26",
          "34",
          "3"
        ],
        [
          "RANCHO NUEVO DE LAS TROJES",
          "2",
          "14",
          "7",
          "7",
          "2"
        ],
        [
          "SAN AGUSTÍN",
          "2",
          "93",
          "44",
          "49",
          "5"
        ],
        [
          "SAN AGUSTÍN SEGUNDO",
          "1",
          "10",
          "7",
          "3",
          "1"
        ],
        [
          "SAN ANTÓN DE LOS MARTÍNEZ",
          "2",
          "24",
          "10",
          "14",
          "2"
        ],
        [
          "SAN ANTONIO DE LAS VIEJAS",
          "2",
          "23",
          "12",
          "11",
          "2"
        ],
        [
          "SAN ANTONIO DE PADUA",
          "1",
          "12",
          "7",
          "5",
          "1"
        ],
        [
          "SAN ANTONIO PRIMERO",
          "2",
          "177",
          "86",
          "91",
          "8"
        ],
        [
          "SAN CAYETANO",
          "2",
          "163",
          "89",
          "74",
          "6"
        ],
        [
          "SAN ERNESTO",
          "2",
          "146",
          "67",
          "79",
          "8"
        ],
        [
          "SAN FRANCISCO UNO",
          "2",
          "22",
          "7",
          "15",
          "2"
        ],
        [
          "SAN IGNACIO",
          "1",
          "47",
          "28",
          "19",
          "2"
        ],
        [
          "SAN ISIDRO",
          "4",
          "436",
          "222",
          "214",
          "17"
        ],
        [
          "SAN JOSÉ DE VISTA HERMOSA",
          "2",
          "36",
          "17",
          "19",
          "2"
        ],
        [
          "SAN JOSÉ DEL CARMEN (EL CASCARERO)",
          "2",
          "122",
          "59",
          "63",
          "6"
        ],
        [
          "SAN JUAN DE LA CRUZ",
          "2",
          "49",
          "25",
          "24",
          "3"
        ],
        [
          "SAN JUAN DE LOS RANGELES",
          "2",
          "41",
          "18",
          "23",
          "2"
        ],
        [
          "SAN JUAN PRIMERO",
          "2",
          "127",
          "61",
          "66",
          "6"
        ],
        [
          "SAN JUAN SEGUNDO",
          "2",
          "28",
          "15",
          "13",
          "2"
        ],
        [
          "SAN LUIS DE LA PAZ",
          "76",
          "16,585",
          "8,612",
          "7,973",
          "917"
        ],
        [
          "SAN MARTÍN",
          "2",
          "80",
          "39",
          "41",
          "5"
        ],
        [
          "SAN NICOLÁS DEL CARMEN",
          "6",
          "946",
          "455",
          "491",
          "45"
        ],
        [
          "SAN PEDRO",
          "2",
          "40",
          "20",
          "20",
          "3"
        ],
        [
          "SAN PEDRO DE LA CRUZ",
          "2",
          "118",
          "58",
          "60",
          "6"
        ],
        [
          "SAN PEDRO DE LOS POZOS (MINERAL DE POZOS)",
          "6",
          "882",
          "411",
          "471",
          "51"
        ],
        [
          "SAN PEDRO DEL DERRAMADERO (LOS PIRULES)",
          "1",
          "16",
          "11",
          "5",
          "1"
        ],
        [
          "SAN RAFAEL",
          "1",
          "68",
          "38",
          "30",
          "3"
        ],
        [
          "SAN RAFAEL DE FÁTIMA",
          "2",
          "48",
          "23",
          "25",
          "3"
        ],
        [
          "SAN RAFAEL DE LA CURVA",
          "1",
          "27",
          "12",
          "15",
          "1"
        ],
        [
          "SANTA MARÍA DE GUADALUPE",
          "1",
          "11",
          "5",
          "6",
          "1"
        ],
        [
          "SANTA ROSA DE OCHOA",
          "1",
          "58",
          "33",
          "25",
          "3"
        ],
        [
          "SANTA TERESITA",
          "2",
          "50",
          "25",
          "25",
          "3"
        ],
        [
          "SANTIAGUILLO",
          "1",
          "5",
          "1",
          "4",
          "1"
        ],
        [
          "TERREROS DE LA CONCEPCIÓN",
          "3",
          "67",
          "26",
          "41",
          "5"
        ],
        [
          "TOREADOR DE ARRIBA",
          "1",
          "13",
          "7",
          "6",
          "1"
        ],
        [
          "TOREADOR DE EN MEDIO",
          "3",
          "337",
          "151",
          "186",
          "14"
        ],
        [
          "VALLE DE GUADALUPE",
          "1",
          "87",
          "40",
          "47",
          "4"
        ],
        [
          "VERGEL DE GUADALUPE",
          "3",
          "174",
          "89",
          "85",
          "8"
        ],
        [
          "VISTA HERMOSA",
          "3",
          "114",
          "69",
          "45",
          "8"
        ],
        [
          "XOCONOXTLE",
          "1",
          "16",
          "9",
          "7",
          "1"
        ],
        [
          "ZAMARRIPA (SAN JOSÉ DE ZAMARRIPA)",
          "2",
          "39",
          "18",
          "21",
          "2"
        ],
        [
          "TOTAL",
          "366",
          "36,719",
          "18,826",
          "17,893",
          "1,943"
        ],
        [
          "¹   Conjunto de individuos adscritos a un centro de trabajo, de acuerdo a la función que realizan en el mismo. A cada uno se le considera tantas veces como en centros de trabajo esté adscrito."
        ],
        [
          "Fuente: Sistema de Estadísticas Continuas de Educación del Formato 911, DGPPyEE, SEP."
        ]
      ]
    },
    {
      "tableIndex": 2,
      "data": [
        [
          "TIPO EDUCATIVO: TODOS;     CONTROL: TODOS;     ENTIDAD: GUANAJUATO;    MUNICIPIO: SAN LUIS DE LA PAZ"
        ],
        [
          "Localidad",
          "Escuelas",
          "Alumnos",
          "Alumnos Mujeres",
          "Alumnos Hombres",
          "Docentes¹"
        ],
        [
          "BERLÍN",
          "1",
          "114",
          "67",
          "47",
          "6"
        ],
        [
          "BUENAVISTA (EL CUERNITO)",
          "2",
          "135",
          "63",
          "72",
          "9"
        ],
        [
          "CERRO BLANCO",
          "2",
          "5",
          "1",
          "4",
          "2"
        ],
        [
          "COLONIA BENITO JUÁREZ",
          "1",
          "51",
          "20",
          "31",
          "3"
        ],
        [
          "COVADONGA",
          "2",
          "131",
          "48",
          "83",
          "7"
        ],
        [
          "DERRAMADERO SEGUNDO (INFIERNILLO)",
          "4",
          "316",
          "154",
          "162",
          "15"
        ],
        [
          "DOLORES SAN JUAN",
          "2",
          "100",
          "51",
          "49",
          "5"
        ],
        [
          "EJIDO SANTA ANA Y LOBOS (FRACCIÓN DE LOURDES)",
          "5",
          "853",
          "443",
          "410",
          "30"
        ],
        [
          "EL BOLUDO",
          "1",
          "11",
          "4",
          "7",
          "1"
        ],
        [
          "EL BOZO",
          "2",
          "24",
          "10",
          "14",
          "2"
        ],
        [
          "EL CHARCO",
          "2",
          "173",
          "93",
          "80",
          "8"
        ],
        [
          "EL CHUPADERO",
          "4",
          "112",
          "59",
          "53",
          "9"
        ],
        [
          "EL MEZOTE (ENTRONQUE DE CHARCAS)",
          "1",
          "10",
          "4",
          "6",
          "1"
        ],
        [
          "EL PAREDÓN",
          "1",
          "10",
          "8",
          "2",
          "1"
        ],
        [
          "EL PRINGÓN",
          "2",
          "109",
          "51",
          "58",
          "5"
        ],
        [
          "EL REALITO (MINERAL EL REALITO)",
          "2",
          "14",
          "4",
          "10",
          "2"
        ],
        [
          "EL REFUGIO (RANCHITO EL REFUGIO)",
          "2",
          "38",
          "22",
          "16",
          "2"
        ],
        [
          "EL SAUZ TRES",
          "2",
          "179",
          "92",
          "87",
          "8"
        ],
        [
          "EL TOREADOR DE ABAJO",
          "2",
          "227",
          "120",
          "107",
          "8"
        ],
        [
          "EL VARAL (LA MERCED)",
          "4",
          "344",
          "173",
          "171",
          "13"
        ],
        [
          "ESPINAS BLANCAS",
          "2",
          "64",
          "37",
          "27",
          "3"
        ],
        [
          "EX-HACIENDA DE ORTEGA (EJIDO ORTEGA)",
          "4",
          "210",
          "86",
          "124",
          "12"
        ],
        [
          "EX-HACIENDA DE SANTA ANA (SANTA ANA Y LOBOS)",
          "1",
          "218",
          "94",
          "124",
          "8"
        ],
        [
          "FRACCIONAMIENTO RESIDENCIAL VILLAS DE LA GLORIA",
          "1",
          "50",
          "23",
          "27",
          "12"
        ],
        [
          "GARIBALDI (EL CERRITO)",
          "2",
          "28",
          "13",
          "15",
          "2"
        ],
        [
          "JOFRE (SAN JOSÉ DE JOFRE)",
          "1",
          "8",
          "0",
          "8",
          "1"
        ],
        [
          "LA ANGELINA (LOS LIEBRILLOS)",
          "2",
          "50",
          "28",
          "22",
          "3"
        ],
        [
          "LA CANTERA",
          "2",
          "92",
          "44",
          "48",
          "5"
        ],
        [
          "LA CAÑADA DEL PUEBLITO",
          "1",
          "8",
          "4",
          "4",
          "1"
        ],
        [
          "LA CIÉNEGA",
          "3",
          "417",
          "212",
          "205",
          "19"
        ],
        [
          "LA CIENEGUILLA DEL REFUGIO",
          "2",
          "55",
          "22",
          "33",
          "4"
        ],
        [
          "LA CONCEPCIÓN (LA CONCHA)",
          "1",
          "8",
          "5",
          "3",
          "1"
        ],
        [
          "LA CRUZ",
          "1",
          "18",
          "8",
          "10",
          "2"
        ],
        [
          "LA CRUZ DE GUERRERO",
          "4",
          "194",
          "99",
          "95",
          "10"
        ],
        [
          "LA ESCOBILLA",
          "2",
          "42",
          "21",
          "21",
          "3"
        ],
        [
          "LA ESCONDIDA",
          "1",
          "6",
          "4",
          "2",
          "1"
        ],
        [
          "LA ESCONDIDITA",
          "3",
          "157",
          "75",
          "82",
          "10"
        ],
        [
          "LA ESQUINA (LA ESQUINA DE LA PURÍSIMA)",
          "4",
          "221",
          "125",
          "96",
          "10"
        ],
        [
          "LA HUERTA",
          "4",
          "1,991",
          "1,101",
          "890",
          "154"
        ],
        [
          "LA JARRILLA",
          "2",
          "39",
          "27",
          "12",
          "2"
        ],
        [
          "LA LAGUNA SECA",
          "2",
          "165",
          "79",
          "86",
          "8"
        ],
        [
          "LA LEONA",
          "2",
          "62",
          "36",
          "26",
          "3"
        ],
        [
          "LA LUZ",
          "2",
          "32",
          "16",
          "16",
          "2"
        ],
        [
          "LA LUZ DE LA ESQUINA",
          "4",
          "408",
          "199",
          "209",
          "17"
        ],
        [
          "LA MESA DE JESÚS",
          "4",
          "95",
          "48",
          "47",
          "8"
        ],
        [
          "LA ONZA",
          "2",
          "14",
          "9",
          "5",
          "2"
        ],
        [
          "LA PEÑITA",
          "1",
          "49",
          "23",
          "26",
          "3"
        ],
        [
          "LA PROVIDENCIA (LA PROVIDENCIA DEL SALITRE)",
          "2",
          "52",
          "30",
          "22",
          "4"
        ],
        [
          "LA QUINTA DOS",
          "2",
          "33",
          "17",
          "16",
          "2"
        ],
        [
          "LA SEMITA",
          "4",
          "112",
          "54",
          "58",
          "8"
        ],
        [
          "LA SOLEDAD",
          "3",
          "206",
          "107",
          "99",
          "11"
        ],
        [
          "LA SOLEDAD DEL MONTE",
          "3",
          "97",
          "43",
          "54",
          "6"
        ],
        [
          "LA TINAJA",
          "2",
          "88",
          "41",
          "47",
          "4"
        ],
        [
          "LA VACIADA",
          "2",
          "31",
          "16",
          "15",
          "2"
        ],
        [
          "LABOR DE GAMBOA",
          "2",
          "66",
          "37",
          "29",
          "3"
        ],
        [
          "LAS NEGRITAS",
          "2",
          "44",
          "22",
          "22",
          "2"
        ],
        [
          "LAS PALOMAS",
          "1",
          "6",
          "3",
          "3",
          "1"
        ],
        [
          "LOS ÁNGELES",
          "4",
          "371",
          "208",
          "163",
          "15"
        ],
        [
          "LOS DOLORES (LAS QUINCE LETRAS)",
          "6",
          "1,149",
          "583",
          "566",
          "38"
        ],
        [
          "LOS PLÁTANOS",
          "2",
          "41",
          "22",
          "19",
          "3"
        ],
        [
          "LOS REMEDIOS",
          "2",
          "52",
          "25",
          "27",
          "3"
        ],
        [
          "LOURDES (ESTACIÓN DE LOURDES)",
          "4",
          "500",
          "255",
          "245",
          "20"
        ],
        [
          "MAGUEY BLANCO",
          "2",
          "175",
          "89",
          "86",
          "7"
        ],
        [
          "MANZANARES",
          "2",
          "57",
          "26",
          "31",
          "3"
        ],
        [
          "MARAVILLAL",
          "2",
          "257",
          "129",
          "128",
          "9"
        ],
        [
          "MATANCILLAS (PUERTO DE MATANCILLAS)",
          "2",
          "59",
          "31",
          "28",
          "4"
        ],
        [
          "MESA DE ESCALANTE",
          "2",
          "26",
          "13",
          "13",
          "2"
        ],
        [
          "MESA DE LA ESTACADA",
          "2",
          "16",
          "6",
          "10",
          "2"
        ],
        [
          "MESA DE PALOTES (MESA DEL CARMEN)",
          "2",
          "36",
          "23",
          "13",
          "2"
        ],
        [
          "MISIÓN DE CHICHIMECAS",
          "9",
          "2,271",
          "1,193",
          "1,078",
          "88"
        ],
        [
          "NORITA DEL REFUGIO",
          "3",
          "129",
          "59",
          "70",
          "7"
        ],
        [
          "NUEVO PASO DE VAQUEROS",
          "2",
          "61",
          "24",
          "37",
          "4"
        ],
        [
          "PALMARITO",
          "2",
          "33",
          "12",
          "21",
          "2"
        ],
        [
          "PALMILLAS",
          "1",
          "6",
          "0",
          "6",
          "1"
        ],
        [
          "PALOS ALTOS",
          "2",
          "174",
          "94",
          "80",
          "8"
        ],
        [
          "PAREDES",
          "2",
          "96",
          "43",
          "53",
          "5"
        ],
        [
          "PASO COLORADO",
          "2",
          "50",
          "24",
          "26",
          "2"
        ],
        [
          "PIEDRAS DE LUMBRE",
          "2",
          "90",
          "35",
          "55",
          "5"
        ],
        [
          "POZO BLANCO",
          "3",
          "177",
          "96",
          "81",
          "8"
        ],
        [
          "POZO BLANCO (ESTACIÓN POZO BLANCO)",
          "3",
          "185",
          "99",
          "86",
          "9"
        ],
        [
          "POZO HONDO (EX-HACIENDA DE POZO HONDO)",
          "3",
          "232",
          "124",
          "108",
          "11"
        ],
        [
          "PROVIDENCIA DE LOS MOLINA",
          "4",
          "181",
          "97",
          "84",
          "10"
        ],
        [
          "PUERTO BLANCO DOS",
          "3",
          "352",
          "192",
          "160",
          "13"
        ],
        [
          "PUERTO DEL GATO",
          "2",
          "33",
          "16",
          "17",
          "2"
        ],
        [
          "PUERTO DEL VARAL",
          "2",
          "8",
          "1",
          "7",
          "2"
        ],
        [
          "PURÍSIMA DE CERRO GRANDE",
          "2",
          "70",
          "36",
          "34",
          "4"
        ],
        [
          "RANCHO DE GUADALUPE (CIUDAD DE LOS NIÑOS)",
          "2",
          "29",
          "17",
          "12",
          "2"
        ],
        [
          "RANCHO NUEVO",
          "2",
          "60",
          "26",
          "34",
          "3"
        ],
        [
          "RANCHO NUEVO DE LAS TROJES",
          "2",
          "14",
          "7",
          "7",
          "2"
        ],
        [
          "SAN AGUSTÍN",
          "2",
          "93",
          "44",
          "49",
          "5"
        ],
        [
          "SAN AGUSTÍN SEGUNDO",
          "1",
          "10",
          "7",
          "3",
          "1"
        ],
        [
          "SAN ANTÓN DE LOS MARTÍNEZ",
          "2",
          "24",
          "10",
          "14",
          "2"
        ],
        [
          "SAN ANTONIO DE LAS VIEJAS",
          "2",
          "23",
          "12",
          "11",
          "2"
        ],
        [
          "SAN ANTONIO DE PADUA",
          "1",
          "12",
          "7",
          "5",
          "1"
        ],
        [
          "SAN ANTONIO PRIMERO",
          "2",
          "177",
          "86",
          "91",
          "8"
        ],
        [
          "SAN CAYETANO",
          "2",
          "163",
          "89",
          "74",
          "6"
        ],
        [
          "SAN ERNESTO",
          "2",
          "146",
          "67",
          "79",
          "8"
        ],
        [
          "SAN FRANCISCO UNO",
          "2",
          "22",
          "7",
          "15",
          "2"
        ],
        [
          "SAN IGNACIO",
          "1",
          "47",
          "28",
          "19",
          "2"
        ],
        [
          "SAN ISIDRO",
          "4",
          "436",
          "222",
          "214",
          "17"
        ],
        [
          "SAN JOSÉ DE VISTA HERMOSA",
          "2",
          "36",
          "17",
          "19",
          "2"
        ],
        [
          "SAN JOSÉ DEL CARMEN (EL CASCARERO)",
          "2",
          "122",
          "59",
          "63",
          "6"
        ],
        [
          "SAN JUAN DE LA CRUZ",
          "2",
          "49",
          "25",
          "24",
          "3"
        ],
        [
          "SAN JUAN DE LOS RANGELES",
          "2",
          "41",
          "18",
          "23",
          "2"
        ],
        [
          "SAN JUAN PRIMERO",
          "2",
          "127",
          "61",
          "66",
          "6"
        ],
        [
          "SAN JUAN SEGUNDO",
          "2",
          "28",
          "15",
          "13",
          "2"
        ],
        [
          "SAN LUIS DE LA PAZ",
          "76",
          "16,585",
          "8,612",
          "7,973",
          "917"
        ],
        [
          "SAN MARTÍN",
          "2",
          "80",
          "39",
          "41",
          "5"
        ],
        [
          "SAN NICOLÁS DEL CARMEN",
          "6",
          "946",
          "455",
          "491",
          "45"
        ],
        [
          "SAN PEDRO",
          "2",
          "40",
          "20",
          "20",
          "3"
        ],
        [
          "SAN PEDRO DE LA CRUZ",
          "2",
          "118",
          "58",
          "60",
          "6"
        ],
        [
          "SAN PEDRO DE LOS POZOS (MINERAL DE POZOS)",
          "6",
          "882",
          "411",
          "471",
          "51"
        ],
        [
          "SAN PEDRO DEL DERRAMADERO (LOS PIRULES)",
          "1",
          "16",
          "11",
          "5",
          "1"
        ],
        [
          "SAN RAFAEL",
          "1",
          "68",
          "38",
          "30",
          "3"
        ],
        [
          "SAN RAFAEL DE FÁTIMA",
          "2",
          "48",
          "23",
          "25",
          "3"
        ],
        [
          "SAN RAFAEL DE LA CURVA",
          "1",
          "27",
          "12",
          "15",
          "1"
        ],
        [
          "SANTA MARÍA DE GUADALUPE",
          "1",
          "11",
          "5",
          "6",
          "1"
        ],
        [
          "SANTA ROSA DE OCHOA",
          "1",
          "58",
          "33",
          "25",
          "3"
        ],
        [
          "SANTA TERESITA",
          "2",
          "50",
          "25",
          "25",
          "3"
        ],
        [
          "SANTIAGUILLO",
          "1",
          "5",
          "1",
          "4",
          "1"
        ],
        [
          "TERREROS DE LA CONCEPCIÓN",
          "3",
          "67",
          "26",
          "41",
          "5"
        ],
        [
          "TOREADOR DE ARRIBA",
          "1",
          "13",
          "7",
          "6",
          "1"
        ],
        [
          "TOREADOR DE EN MEDIO",
          "3",
          "337",
          "151",
          "186",
          "14"
        ],
        [
          "VALLE DE GUADALUPE",
          "1",
          "87",
          "40",
          "47",
          "4"
        ],
        [
          "VERGEL DE GUADALUPE",
          "3",
          "174",
          "89",
          "85",
          "8"
        ],
        [
          "VISTA HERMOSA",
          "3",
          "114",
          "69",
          "45",
          "8"
        ],
        [
          "XOCONOXTLE",
          "1",
          "16",
          "9",
          "7",
          "1"
        ],
        [
          "ZAMARRIPA (SAN JOSÉ DE ZAMARRIPA)",
          "2",
          "39",
          "18",
          "21",
          "2"
        ],
        [
          "TOTAL",
          "366",
          "36,719",
          "18,826",
          "17,893",
          "1,943"
        ],
        [
          "¹   Conjunto de individuos adscritos a un centro de trabajo, de acuerdo a la función que realizan en el mismo. A cada uno se le considera tantas veces como en centros de trabajo esté adscrito."
        ],
        [
          "Fuente: Sistema de Estadísticas Continuas de Educación del Formato 911, DGPPyEE, SEP."
        ]
      ]
    }
  ],
  "timestamp": "2025-10-31T07:10:44.709Z"
}